vlc_controller/__init__.py
vlc_controller-0.0.6.dist-info/METADATA
vlc_controller-0.0.6.dist-info/WHEEL
vlc_controller-0.0.6.dist-info/top_level.txt
vlc_controller-0.0.6.dist-info/RECORD
