Metadata-Version: 2.1
Name: vlc-controller
Version: 0.0.6
Summary: VLC Controller
Home-page: https://github.com/48723247842/VLCController
Author: 7435171
Author-email: 48723247842@protonmail.com
License: UNKNOWN
Platform: UNKNOWN
Classifier: Programming Language :: Python :: 3
Classifier: License :: OSI Approved :: MIT License
Classifier: Operating System :: OS Independent
Requires-Python: >=3.8
